francium/__init__.py
francium/algorithms/__init__.py
francium/algorithms/genetic_algorithm/__init__.py
francium/algorithms/genetic_algorithm/agent.py
francium/algorithms/genetic_algorithm/environment.py
francium/algorithms/genetic_algorithm/solver.py
francium/algorithms/hill_climbing/__init__.py
francium/algorithms/hill_climbing/agent.py
francium/algorithms/hill_climbing/environment.py
francium/algorithms/hill_climbing/solver.py
francium/algorithms/simulated_annealing/__init__.py
francium/algorithms/simulated_annealing/agent.py
francium/algorithms/simulated_annealing/environment.py
francium/algorithms/simulated_annealing/solver.py
francium/core/__init__.py
francium/core/agent.py
francium/core/environment.py
francium/core/eval_functions.py
francium/core/logger.py
francium/core/memory.py
francium/core/solver.py
francium/core/state.py
francium-0.0.3.dev1.dist-info/METADATA
francium-0.0.3.dev1.dist-info/WHEEL
francium-0.0.3.dev1.dist-info/top_level.txt
francium-0.0.3.dev1.dist-info/RECORD
