Metadata-Version: 2.1
Name: francium
Version: 0.0.3.dev1
Summary: A simple library for testing out AI Algorithms
Home-page: https://github.com/satyajitghana/ProjektFrancium
Author: Satyajit Ghana
Author-email: satyajitghana7@gmail.com
License: UNKNOWN
Platform: UNKNOWN
Classifier: Programming Language :: Python :: 3
Classifier: License :: OSI Approved :: MIT License
Classifier: Operating System :: OS Independent
Requires-Python: >=3.6
Requires-Dist: numpy (~=1.19.2)
Requires-Dist: matplotlib (~=2.2.5)
Requires-Dist: seaborn (~=0.11.0)
